chalice_mail/__init__.py
chalice_mail/_errors.py
chalice_mail/errors.py
chalice_mail/mail.py
chalice_mail/message.py
chalice_mail/render_template.py
chalice_mail-0.0.1.dist-info/METADATA
chalice_mail-0.0.1.dist-info/WHEEL
chalice_mail-0.0.1.dist-info/top_level.txt
chalice_mail-0.0.1.dist-info/RECORD
