Metadata-Version: 2.1
Name: chalice-mail
Version: 0.0.1
Summary: SMTP and SES mail integration with AWS Chalice
Home-page: https://github.com/marktennyson/chalice-mail
Author: Aniket Sarkar
Author-email: aniketsarkar@yahoo.com
License: MIT
Keywords: chalice,email,smtp mail,aws,ses
Platform: any
Classifier: Development Status :: 5 - Production/Stable
Classifier: Environment :: Web Environment
Classifier: Intended Audience :: Developers
Classifier: License :: OSI Approved :: MIT License
Classifier: Operating System :: OS Independent
Classifier: Programming Language :: Python
Classifier: Programming Language :: Python :: 3
Classifier: Programming Language :: Python :: 3 :: Only
Classifier: Programming Language :: Python :: 3.6
Classifier: Programming Language :: Python :: 3.7
Classifier: Programming Language :: Python :: 3.8
Classifier: Programming Language :: Python :: 3.9
Classifier: Programming Language :: Python :: Implementation :: CPython
Classifier: Programming Language :: Python :: Implementation :: PyPy
Classifier: Topic :: Software Development :: Libraries :: Python Modules
Requires-Python: >=3.6,<4
Requires-Dist: appdirs (==1.4.4)
Requires-Dist: attrs (==20.3.0)
Requires-Dist: blessed (==1.17.6)
Requires-Dist: blessings (==1.7)
Requires-Dist: boto3 (==1.17.52)
Requires-Dist: botocore (==1.20.52)
Requires-Dist: certifi (==2020.12.5)
Requires-Dist: chalice (==1.22.3)
Requires-Dist: chardet (==4.0.0)
Requires-Dist: click (==7.1.2)
Requires-Dist: codecov (==2.1.11)
Requires-Dist: coloredlogs (==15.0)
Requires-Dist: colour-runner (==0.1.1)
Requires-Dist: coverage (==5.5)
Requires-Dist: deepdiff (==5.2.3)
Requires-Dist: distlib (==0.3.1)
Requires-Dist: filelock (==3.0.12)
Requires-Dist: humanfriendly (==9.1)
Requires-Dist: idna (==2.10)
Requires-Dist: inquirer (==2.7.0)
Requires-Dist: Jinja2 (==2.11.3)
Requires-Dist: jmespath (==0.10.0)
Requires-Dist: MarkupSafe (==1.1.1)
Requires-Dist: mypy-extensions (==0.4.3)
Requires-Dist: ordered-set (==4.0.2)
Requires-Dist: packaging (==20.9)
Requires-Dist: pluggy (==0.13.1)
Requires-Dist: py (==1.10.0)
Requires-Dist: Pygments (==2.8.1)
Requires-Dist: pyparsing (==2.4.7)
Requires-Dist: python-dateutil (==2.8.1)
Requires-Dist: python-editor (==1.0.4)
Requires-Dist: PyYAML (==5.4.1)
Requires-Dist: readchar (==2.0.1)
Requires-Dist: requests (==2.25.1)
Requires-Dist: rootpath (==0.1.1)
Requires-Dist: s3transfer (==0.3.7)
Requires-Dist: six (==1.15.0)
Requires-Dist: termcolor (==1.1.0)
Requires-Dist: toml (==0.10.2)
Requires-Dist: tox (==3.23.0)
Requires-Dist: urllib3 (==1.26.4)
Requires-Dist: virtualenv (==20.4.3)
Requires-Dist: wcwidth (==0.2.5)
